pyopenweathermap/__init__.py
pyopenweathermap/client/free_client.py
pyopenweathermap/client/onecall_client.py
pyopenweathermap/client/owm_abstract_client.py
pyopenweathermap/client/owm_client_factory.py
pyopenweathermap/data_converter.py
pyopenweathermap/exception.py
pyopenweathermap/http_client.py
pyopenweathermap/weather.py
pyopenweathermap-0.2.1.dist-info/LICENSE
pyopenweathermap-0.2.1.dist-info/METADATA
pyopenweathermap-0.2.1.dist-info/WHEEL
pyopenweathermap-0.2.1.dist-info/RECORD
