Metadata-Version: 2.1
Name: pyopenweathermap
Version: 0.2.1
Summary: lib for OpenWeatherMap for Home Assistant
Home-page: https://github.com/freekode/pyopenweathermap
License: MIT
Keywords: homeassistant,owm,openweathermap
Author: Evgeny
Author-email: iam@freekode.org
Requires-Python: >=3.11,<4.0
Classifier: License :: OSI Approved :: MIT License
Classifier: Programming Language :: Python :: 3
Classifier: Programming Language :: Python :: 3.11
Classifier: Programming Language :: Python :: 3.12
Classifier: Programming Language :: Python :: 3.13
Requires-Dist: aiohttp (>=3.9.5,<4.0.0)
Project-URL: Repository, https://github.com/freekode/pyopenweathermap
